pykoala/__init__.py
pykoala/api_client.py
pykoala/configuration.py
pykoala/rest.py
pykoala/api/__init__.py
pykoala/api/config_api.py
pykoala/api/job_api.py
pykoala/api/model_api.py
pykoala/api/runner_api.py
pykoala/models/__init__.py
pykoala/models/color_mode.py
pykoala/models/created_message.py
pykoala/models/deleted_message.py
pykoala/models/error.py
pykoala/models/id_list.py
pykoala/models/image.py
pykoala/models/image_url.py
pykoala/models/inline_response_200.py
pykoala/models/job_canceled.py
pykoala/models/job_failed.py
pykoala/models/job_queued.py
pykoala/models/job_request.py
pykoala/models/job_running.py
pykoala/models/job_setup.py
pykoala/models/job_starting.py
pykoala/models/job_status.py
pykoala/models/job_successful.py
pykoala/models/job_waiting.py
pykoala/models/label_filter.py
pykoala/models/lat_lon_bounding_box.py
pykoala/models/lat_lon_coord.py
pykoala/models/message.py
pykoala/models/model_metadata.py
pykoala/models/point.py
pykoala/models/r2_p_properties.py
pykoala/models/runner_idle.py
pykoala/models/runner_request.py
pykoala/models/runner_running.py
pykoala/models/runner_starting.py
pykoala/models/runner_status.py
pykoala/models/runner_stopping.py
pykoala/models/service_version.py
pykoala/models/size.py
pykoala/models/size_step.py
pykoala/models/version.py
pykoala-1.1.dev131.dist-info/DESCRIPTION.rst
pykoala-1.1.dev131.dist-info/METADATA
pykoala-1.1.dev131.dist-info/RECORD
pykoala-1.1.dev131.dist-info/WHEEL
pykoala-1.1.dev131.dist-info/metadata.json
pykoala-1.1.dev131.dist-info/top_level.txt
