Metadata-Version: 2.0
Name: pykoala
Version: 1.1.dev131
Summary: KOALA
Home-page: http://deepcore.io
Author: Radiant Solutions
Author-email: deepcore-support@digitalglobe.com
License: UNKNOWN
Keywords: Swagger,KOALA,machine learning,neural network
Platform: UNKNOWN
Classifier: License :: OSI Approved :: Apache Software License
Classifier: Development Status :: 4 - Beta
Classifier: Operating System :: POSIX :: Linux
Classifier: Topic :: Scientific/Engineering :: Artificial Intelligence
Requires-Dist: certifi
Requires-Dist: python-dateutil
Requires-Dist: six (>=1.10)
Requires-Dist: urllib3 (>=1.15)
